[{"id":"前言","content":"前言"},{"id":"jmm-基础","content":"JMM 基础"},{"id":"并发编程的两个关键问题","content":"并发编程的两个关键问题"},{"id":"jmm-内存模型抽象结构","content":"JMM 内存模型抽象结构"},{"id":"从源代码到指令序列的重排序","content":"从源代码到指令序列的重排序"},{"id":"数据依赖性","content":"数据依赖性"},{"id":"as-if-serial-语义","content":"as-if-serial 语义"},{"id":"happens-before-关系和-jmm-的设计意图","content":"happens-before 关系和 JMM 的设计意图"},{"id":"jmm-的设计","content":"JMM 的设计"},{"id":"happens-before-关系是什么？","content":"happens-before 关系是什么？"},{"id":"happens-before-规则","content":"happens-before 规则"},{"id":"happens-before-应用例子","content":"happens-before 应用例子"},{"id":"程序顺序规则","content":"程序顺序规则"},{"id":"volatile-的内存语义","content":"volatile 的内存语义"},{"id":"特性","content":"特性"},{"id":"从-happens-before-关系看-volatile-的写-读","content":"从 happens-before 关系看 volatile 的写-读"},{"id":"volatile-写-读的内存语义","content":"volatile 写-读的内存语义"},{"id":"写-volatile-变量内存语义","content":"写 volatile 变量内存语义"},{"id":"读-volatile-内存语义","content":"读 volatile 内存语义"},{"id":"锁的内存语义","content":"锁的内存语义"},{"id":"从-happens-before-关系看锁的释放和获取","content":"从 happens-before 关系看锁的释放和获取"},{"id":"锁的释放和获取的内存语义","content":"锁的释放和获取的内存语义"},{"id":"锁的内存语义的实现","content":"锁的内存语义的实现"}]