[{"id":"definition-of-machine-learning","content":"Definition of Machine Learning"},{"id":"supervised-learning","content":"Supervised Learning"},{"id":"regression-problem","content":"Regression Problem"},{"id":"classification-problem","content":"Classification Problem"},{"id":"univariate-linear-regression","content":"Univariate Linear Regression"},{"id":"the-cost-function","content":"The Cost Function"},{"id":"cost-function-intuition-i","content":"Cost Function Intuition I"},{"id":"gradient-decent","content":"Gradient Decent"},{"id":"gradient-descent-intuition","content":"Gradient Descent Intuition"},{"id":"how-does-gradient-descent-converge-with-a-fixed-step-size-alpha","content":"How does gradient descent converge with a fixed step size α?"},{"id":"gradient-descent-for-linear-regression","content":"Gradient Descent for Linear Regression"}]