[{"id":"46-permutationmedium","content":"46. Permutation(Medium)"},{"id":"backtracking","content":"Backtracking"},{"id":"47-permutation-iimedium","content":"47. Permutation II(Medium)"},{"id":"backtracking-1","content":"Backtracking"},{"id":"48-rotate-imagemedium","content":"48. Rotate Image(Medium)"},{"id":"think-in-the-smart-way","content":"Think In The Smart Way"},{"id":"49-group-anagramsmedium","content":"49. Group Anagrams(Medium)"},{"id":"hashing","content":"Hashing"},{"id":"50-powx-n-medium","content":"50. Pow(x, n) (Medium)"},{"id":"recursion","content":"Recursion"}]