[{"id":"mysql","level":2,"content":"MySQL","child":[{"id":"数据库三范式","level":3,"content":"数据库三范式","child":[]},{"id":"mysql-用户管理","level":3,"content":"MySQL 用户管理","child":[]},{"id":"mysql-自己更新自己","level":3,"content":"MySQL 自己更新自己","child":[]},{"id":"mysql-系统体系架构","level":3,"content":"MySQL 系统体系架构","child":[]},{"id":"mysql-各引擎介绍","level":3,"content":"MySQL 各引擎介绍","child":[]},{"id":"mysql-文件有哪些","level":3,"content":"MySQL 文件有哪些","child":[{"id":"日志文件","level":4,"content":"日志文件","child":[{"id":"错误日志","level":5,"content":"错误日志","child":[]},{"id":"慢查询日志","level":5,"content":"慢查询日志","child":[]},{"id":"查询日志","level":5,"content":"查询日志","child":[]},{"id":"二进制日志","level":5,"content":"二进制日志","child":[]},{"id":"innodb-存储引擎文件","level":5,"content":"InnoDB 存储引擎文件","child":[]}]},{"id":"其他文件","level":4,"content":"其他文件","child":[]}]},{"id":"innodb-逻辑存储结构","level":3,"content":"InnoDB 逻辑存储结构","child":[]},{"id":"innodb-约束类型概念","level":3,"content":"InnoDB 约束类型&概念","child":[]},{"id":"触发器概念","level":3,"content":"触发器概念","child":[]},{"id":"视图概念","level":3,"content":"视图概念","child":[]},{"id":"事务-acid","level":3,"content":"事务 ACID","child":[]},{"id":"sql-事务隔离级别","level":3,"content":"SQL 事务隔离级别","child":[]},{"id":"多版本并发控制（mvcc）","level":3,"content":"多版本并发控制（MVCC）","child":[]},{"id":"mysql-中的死锁","level":3,"content":"MySQL 中的死锁","child":[]},{"id":"mysql-备份","level":3,"content":"MySQL 备份","child":[]},{"id":"mysql-复制","level":3,"content":"MySQL 复制","child":[{"id":"复制要解决的问题","level":4,"content":"复制要解决的问题","child":[]}]},{"id":"select-count-细节","level":3,"content":"Select count 细节","child":[{"id":"函数用法","level":4,"content":"函数用法","child":[]},{"id":"相关问题","level":4,"content":"相关问题","child":[]}]},{"id":"mysql-内存占用太大","level":3,"content":"MySQL 内存占用太大","child":[]}]}]